alexandria_library/__init__.py
alexandria_library/about.py
alexandria_library/desktop.py
alexandria_library/librarian.py
alexandria_library/icons/logo.png
alexandria_library/modules/__init__.py
alexandria_library/modules/about_window.py
alexandria_library/modules/bibtex.py
alexandria_library/modules/configure.py
alexandria_library/modules/context_menu.py
alexandria_library/modules/files.py
alexandria_library/modules/filetypes.py
alexandria_library/modules/message.py
alexandria_library/modules/pdfs.py
alexandria_library/modules/proxy.py
alexandria_library/modules/search_results.py
alexandria_library/modules/worker.py
alexandria_library-0.1.4.dist-info/licenses/LICENSE
alexandria_library-0.1.4.dist-info/METADATA
alexandria_library-0.1.4.dist-info/WHEEL
alexandria_library-0.1.4.dist-info/entry_points.txt
alexandria_library-0.1.4.dist-info/top_level.txt
alexandria_library-0.1.4.dist-info/RECORD
