Metadata-Version: 2.4
Name: alexandria_library
Version: 0.1.4
Summary: Program for the management and organization of digital files.
Author-email: Fernando Pujaico Rivera <fernando.pujaico.rivera@gmail.com>
Maintainer-email: Fernando Pujaico Rivera <fernando.pujaico.rivera@gmail.com>
License-Expression: GPL-3.0-only WITH Classpath-exception-2.0 OR BSD-3-Clause
Project-URL: Bug Reports, https://github.com/trucomanx/AlexandriaLibrary/issues
Project-URL: Funding, https://trucomanx.github.io/en/funding.html
Project-URL: Documentation, https://github.com/trucomanx/AlexandriaLibrary/tree/main/doc
Project-URL: Source, https://github.com/trucomanx/AlexandriaLibrary
Keywords: library,management,organizer
Classifier: Programming Language :: Python :: 3
Classifier: Operating System :: OS Independent
Requires-Python: >=3.8
License-File: LICENSE
Requires-Dist: PyQt5
Requires-Dist: PyPDF2
Requires-Dist: scholarly
Dynamic: license-file
